rio_faux/__init__.py
rio_faux/cli.py
rio_faux-0.2.1.dist-info/entry_points.txt
rio_faux-0.2.1.dist-info/LICENSE
rio_faux-0.2.1.dist-info/WHEEL
rio_faux-0.2.1.dist-info/METADATA
rio_faux-0.2.1.dist-info/RECORD
