Metadata-Version: 2.1
Name: rio-faux
Version: 0.2.1
Summary: Create empty image from a model.
Keywords: rasterio
Author-email: Vincent Sarago <vincent@developmentseed.com>
Requires-Python: >=3.8
Classifier: Intended Audience :: Information Technology
Classifier: Intended Audience :: Science/Research
Classifier: License :: OSI Approved :: BSD License
Classifier: Programming Language :: Python :: 3.8
Classifier: Programming Language :: Python :: 3.9
Classifier: Programming Language :: Python :: 3.10
Classifier: Programming Language :: Python :: 3.11
Classifier: Topic :: Scientific/Engineering :: GIS
Requires-Dist: click>=7.0
Requires-Dist: rasterio>=1.1
Requires-Dist: pre-commit ; extra == "dev"
Requires-Dist: mkdocs ; extra == "docs"
Requires-Dist: mkdocs-material ; extra == "docs"
Requires-Dist: pytest ; extra == "test"
Requires-Dist: pytest-cov ; extra == "test"
Project-URL: Documentation, https://cogeotiff.github.io/rio-faux/
Project-URL: Source, https://github.com/cogeotiff/rio-faux
Provides-Extra: dev
Provides-Extra: docs
Provides-Extra: test
